nextline_alert/__about__.py
nextline_alert/__init__.py
nextline_alert/default.toml
nextline_alert/emitter.py
nextline_alert/plugin.py
nextline_alert/py.typed
nextline_alert/alerts/__init__.py
nextline_alert/alerts/idle.py
nextline_alert/alerts/run_failed.py
nextline_alert/alerts/types.py
nextline_alert/graphql/__init__.py
nextline_alert/graphql/queries/Version.gql
nextline_alert/schema/__init__.py
nextline_alert/schema/query.py
nextline_alert-0.10.0.dist-info/METADATA
nextline_alert-0.10.0.dist-info/WHEEL
nextline_alert-0.10.0.dist-info/entry_points.txt
nextline_alert-0.10.0.dist-info/licenses/LICENSE.txt
nextline_alert-0.10.0.dist-info/RECORD
