Metadata-Version: 2.4
Name: nextline-alert
Version: 0.10.0
Summary: A plugin of nextline-graphql. Emit alerts to Campana
Project-URL: Documentation, https://github.com/simonsobs/nextline-alert#readme
Project-URL: Issues, https://github.com/simonsobs/nextline-alert/issues
Project-URL: Source, https://github.com/simonsobs/nextline-alert
Author-email: Simons Observatory <so_software@simonsobservatory.org>
License-Expression: MIT
License-File: LICENSE.txt
Classifier: Development Status :: 4 - Beta
Classifier: Intended Audience :: Science/Research
Classifier: License :: OSI Approved :: MIT License
Classifier: Programming Language :: Python
Classifier: Programming Language :: Python :: 3.10
Classifier: Programming Language :: Python :: 3.11
Classifier: Programming Language :: Python :: 3.12
Classifier: Programming Language :: Python :: 3.13
Requires-Python: >=3.10
Requires-Dist: httpx>=0.26
Requires-Dist: nextline-graphql>=0.7.8
Provides-Extra: tests
Requires-Dist: deepdiff>=7.0; extra == 'tests'
Requires-Dist: hypothesis>=6.130; extra == 'tests'
Requires-Dist: pytest-asyncio>=0.23; extra == 'tests'
Requires-Dist: pytest-cov>=4.1; extra == 'tests'
Requires-Dist: pytest-timeout>=2.2; extra == 'tests'
Requires-Dist: pytest>=7.4; extra == 'tests'
Requires-Dist: respx>=0.20.1; extra == 'tests'
